setup.py
useful_dist/Binomialdistribution.py
useful_dist/Gaussiandistribution.py
useful_dist/Generaldistribution.py
useful_dist/__init__.py
useful_dist.egg-info/PKG-INFO
useful_dist.egg-info/SOURCES.txt
useful_dist.egg-info/dependency_links.txt
useful_dist.egg-info/not-zip-safe
useful_dist.egg-info/top_level.txt